upandup/__init__.py
upandup/load.py
upandup/serializer.py
upandup/updater.py
upandup-0.1.0.dist-info/LICENSE
upandup-0.1.0.dist-info/METADATA
upandup-0.1.0.dist-info/WHEEL
upandup-0.1.0.dist-info/top_level.txt
upandup-0.1.0.dist-info/RECORD
