Metadata-Version: 2.1
Name: upandup
Version: 0.1.0
Summary: A simple schema versioning system for Python dataclasses
Home-page: https://github.com/smrfeld/upandup
License: MIT
Requires-Python: >=3.11
License-File: LICENSE
Requires-Dist: loguru
Requires-Dist: mashumaro
Requires-Dist: pytest
Requires-Dist: setuptools
